soia/__init__.py
soia/_module_initializer.py
soia/_spec.py
soia/reflection.py
soia/_impl/__init__.py
soia/_impl/arrays.py
soia/_impl/binary.py
soia/_impl/enums.py
soia/_impl/function_maker.py
soia/_impl/keep.py
soia/_impl/keyed_items.py
soia/_impl/method.py
soia/_impl/never.py
soia/_impl/optionals.py
soia/_impl/primitives.py
soia/_impl/repr.py
soia/_impl/serializer.py
soia/_impl/serializers.py
soia/_impl/service.py
soia/_impl/service_client.py
soia/_impl/structs.py
soia/_impl/timestamp.py
soia/_impl/type_adapter.py
soia_client-1.2.0.dist-info/licenses/LICENSE
soia_client-1.2.0.dist-info/METADATA
soia_client-1.2.0.dist-info/WHEEL
soia_client-1.2.0.dist-info/top_level.txt
soia_client-1.2.0.dist-info/RECORD
